MANIFEST.in
README.md
setup.cfg
setup.py
scripts/sis
sis.egg-info/PKG-INFO
sis.egg-info/SOURCES.txt
sis.egg-info/dependency_links.txt
sis.egg-info/requires.txt
sis.egg-info/top_level.txt
src/sis/__init__.py
src/sis/sisyphus.py