Metadata-Version: 1.1
Name: sis
Version: 0.1.4
Summary: Sisyphus command runner
Home-page: http://github.com/lordi/sisyphus
Author: Hannes Gräuler
Author-email: hgraeule@uos.de
License: MIT
Download-URL: https://github.com/lordi/sisyphus/tarball/v0.1.4
Platform: UNKNOWN
Classifier: Development Status :: 3 - Alpha
Classifier: Intended Audience :: Developers
Classifier: Environment :: Console
Classifier: License :: OSI Approved :: MIT License
Classifier: Operating System :: POSIX :: Linux
Classifier: Programming Language :: Python :: 2
Classifier: Programming Language :: Python :: 3
